LICENSE
MANIFEST.in
README.md
setup.py
hlpl_english_words_synonym_antonym/__init__.py
hlpl_english_words_synonym_antonym/__main__.py
hlpl_english_words_synonym_antonym/english_words_synonym_antonym.py
hlpl_english_words_synonym_antonym/hlpl_english_words_synonym_antonym.db
hlpl_english_words_synonym_antonym/setup.cfg
hlpl_english_words_synonym_antonym.egg-info/PKG-INFO
hlpl_english_words_synonym_antonym.egg-info/SOURCES.txt
hlpl_english_words_synonym_antonym.egg-info/dependency_links.txt
hlpl_english_words_synonym_antonym.egg-info/entry_points.txt
hlpl_english_words_synonym_antonym.egg-info/top_level.txt