Metadata-Version: 2.1
Name: hlpl-english-words-synonym-antonym
Version: 1.0.0
Summary: hlpl_english_words_synonym_antonym lists english words synonyms and antonyms in readable database python package
Home-page: https://hlpl.net/resources
Author: Ahmida Bendjoudi
Author-email: email@hlpl.net
License: MIT
Download-URL: https://hlpl.net/resources/download/
Project-URL: hlpl, https://hlpl.net
Project-URL: hlpl_synonym_antonym-docs, https://docs.hlpl.net
Project-URL: hlpl_synonym_antonym-forum, https://hlpl.net/hlpl-forums
Project-URL: hlpl_synonym_antonym-github, https://github.com/hlpl/english-words-synonym-antonym
Keywords: hlpl_english_words_synonym_antonym,hlpl english words synonym antonym,english words synonym antonym,hlpl english words synonym antonym,hlpl,synonym antonym,words synonym antonym
Platform: UNKNOWN
Classifier: Natural Language :: English
Requires-Python: >=3, <=3.9
License-File: LICENSE
